tkdocviewer/__init__.py
tkdocviewer/__main__.py
tkdocviewer/rendering.py
tkdocviewer/test.py
tkdocviewer/widget.py
tkdocviewer/backends/__init__.py
tkdocviewer/backends/ghostscript.py
tkdocviewer/backends/ghostxps.py
tkdocviewer/backends/pil_multiframe.py
tkdocviewer/backends/shared.py
tkdocviewer/backends/util.py
tkDocViewer-2.0.2.dist-info/LICENSE
tkDocViewer-2.0.2.dist-info/METADATA
tkDocViewer-2.0.2.dist-info/WHEEL
tkDocViewer-2.0.2.dist-info/top_level.txt
tkDocViewer-2.0.2.dist-info/RECORD
