Metadata-Version: 2.1
Name: tkDocViewer
Version: 2.0.2
Summary: Document viewer widget for Tkinter
Home-page: https://github.com/bmjcode/tkDocViewer
Author: Benjamin Johnson
Author-email: bmjcode@gmail.com
License: UNKNOWN
Platform: UNKNOWN
Classifier: Development Status :: 7 - Inactive
Classifier: Programming Language :: Python :: 2
Classifier: Programming Language :: Python :: 3
Classifier: License :: OSI Approved :: MIT License
Classifier: Operating System :: OS Independent
